<?xml version="1.0"?>
<ruleset name="ScribeJava PMD ruleset"
         xmlns="http://pmd.sourceforge.net/ruleset/2.0.0"
         xmlns:xsi="http://www.w3.org/2001/XMLSchema-instance"
         xsi:schemaLocation="http://pmd.sourceforge.net/ruleset/2.0.0 http://pmd.sourceforge.net/ruleset_2_0_0.xsd">

    <description>
        This ruleset defines the PMD rules for project "ScribeJava".
    </description>

    <rule ref="category/java/bestpractices.xml/AvoidPrintStackTrace" />
    <rule ref="category/java/bestpractices.xml/MissingOverride" />
    <rule ref="category/java/bestpractices.xml/OneDeclarationPerLine">
        <properties>
            <property name="strictMode">true</property>
        </properties>
    </rule>
    <rule ref="category/java/bestpractices.xml/SwitchStmtsShouldHaveDefault" />
    <rule ref="category/java/bestpractices.xml/SystemPrintln" />
    <rule ref="category/java/bestpractices.xml/UnusedImports" />
    <rule ref="category/java/bestpractices.xml/UnusedLocalVariable" />
    <rule ref="category/java/bestpractices.xml/UseAssertNullInsteadOfAssertTrue" />
    <rule ref="category/java/bestpractices.xml/UseAssertSameInsteadOfAssertTrue" />
    <rule ref="category/java/bestpractices.xml/UseAssertTrueInsteadOfAssertEquals" />
    <rule ref="category/java/bestpractices.xml/UseCollectionIsEmpty" />
    <rule ref="category/java/bestpractices.xml/UseTryWithResources" />

    <rule ref="category/java/codestyle.xml/AvoidDollarSigns" />
    <rule ref="category/java/codestyle.xml/AvoidProtectedFieldInFinalClass" />
    <rule ref="category/java/codestyle.xml/AvoidProtectedMethodInFinalClassNotExtending" />
    <rule ref="category/java/codestyle.xml/BooleanGetMethodName">
        <properties>
            <property name="checkParameterizedMethods">true</property>
        </properties>
    </rule>
    <rule ref="category/java/codestyle.xml/ControlStatementBraces" />
    <rule ref="category/java/codestyle.xml/DontImportJavaLang" />
    <rule ref="category/java/codestyle.xml/DuplicateImports" />
    <rule ref="category/java/codestyle.xml/ExtendsObject" />
    <rule ref="category/java/codestyle.xml/FieldNamingConventions" />
    <rule ref="category/java/codestyle.xml/ForLoopShouldBeWhileLoop" />
    <rule ref="category/java/codestyle.xml/FormalParameterNamingConventions" />
    <rule ref="category/java/codestyle.xml/IdenticalCatchBranches" />
    <rule ref="category/java/codestyle.xml/LocalVariableNamingConventions" />
    <rule ref="category/java/codestyle.xml/MethodNamingConventions" />
    <rule ref="category/java/codestyle.xml/NoPackage" />
    <rule ref="category/java/codestyle.xml/PackageCase" />
    <rule ref="category/java/codestyle.xml/UnnecessaryAnnotationValueElement" />
    <rule ref="category/java/codestyle.xml/UnnecessaryConstructor" />
    <rule ref="category/java/codestyle.xml/UnnecessaryFullyQualifiedName" />
    <rule ref="category/java/codestyle.xml/UnnecessaryModifier" />
    <rule ref="category/java/codestyle.xml/UnnecessaryReturn" />
    <rule ref="category/java/codestyle.xml/UselessParentheses" />
    <rule ref="category/java/codestyle.xml/UselessQualifiedThis" />
    <rule ref="category/java/design.xml/AbstractClassWithoutAnyMethod" />
    <rule ref="category/java/design.xml/AvoidThrowingNewInstanceOfSameException" />
    <rule ref="category/java/design.xml/CollapsibleIfStatements" />
    <rule ref="category/java/design.xml/DoNotExtendJavaLangError" />
    <rule ref="category/java/design.xml/LogicInversion" />
    <rule ref="category/java/design.xml/SimplifiedTernary" />
    <rule ref="category/java/design.xml/SimplifyBooleanAssertion" />
    <rule ref="category/java/design.xml/SimplifyBooleanExpressions" />
    <rule ref="category/java/design.xml/SimplifyBooleanReturns" />
    <rule ref="category/java/design.xml/SimplifyConditional" />
    <rule ref="category/java/design.xml/UseUtilityClass" />
    <rule ref="category/java/errorprone.xml/AvoidAssertAsIdentifier" />
    <rule ref="category/java/errorprone.xml/AvoidBranchingStatementAsLastInLoop" />
    <rule ref="category/java/errorprone.xml/AvoidCallingFinalize" />
    <rule ref="category/java/errorprone.xml/AvoidEnumAsIdentifier" />
    <rule ref="category/java/errorprone.xml/AvoidLosingExceptionInformation" />
    <rule ref="category/java/errorprone.xml/AvoidMultipleUnaryOperators" />
</ruleset>
